pywebtask-0.27.0.dist-info/licenses/LICENSE
webtask/__init__.py
webtask/constants.py
webtask/exceptions.py
webtask/webtask.py
webtask/_internal/config.py
webtask/_internal/accessibility/__init__.py
webtask/_internal/accessibility/axnode.py
webtask/_internal/accessibility/filters/__init__.py
webtask/_internal/accessibility/filters/filter_duplicate_names.py
webtask/_internal/accessibility/filters/filter_ignored.py
webtask/_internal/accessibility/filters/filter_non_semantic_role.py
webtask/_internal/accessibility/parsers/__init__.py
webtask/_internal/accessibility/parsers/cdp.py
webtask/_internal/agent/__init__.py
webtask/_internal/agent/agent_browser.py
webtask/_internal/agent/file_manager.py
webtask/_internal/agent/message.py
webtask/_internal/agent/run.py
webtask/_internal/agent/selector.py
webtask/_internal/agent/task_runner.py
webtask/_internal/agent/tool_registry.py
webtask/_internal/agent/tools/__init__.py
webtask/_internal/agent/tools/control.py
webtask/_internal/agent/tools/dom.py
webtask/_internal/agent/tools/navigation.py
webtask/_internal/agent/tools/pixel.py
webtask/_internal/agent/tools/tab.py
webtask/_internal/agent/tools/utility.py
webtask/_internal/context/__init__.py
webtask/_internal/context/llm_dom_context.py
webtask/_internal/dom/__init__.py
webtask/_internal/dom/domnode.py
webtask/_internal/dom/selector.py
webtask/_internal/dom/filters/__init__.py
webtask/_internal/dom/filters/filter_non_rendered.py
webtask/_internal/dom/filters/filter_non_semantic.py
webtask/_internal/dom/knowledge/__init__.py
webtask/_internal/dom/knowledge/interactive.py
webtask/_internal/dom/knowledge/rendering.py
webtask/_internal/dom/knowledge/semantic.py
webtask/_internal/dom/parsers/__init__.py
webtask/_internal/dom/parsers/cdp.py
webtask/_internal/dom/parsers/html.py
webtask/_internal/dom/serializers/__init__.py
webtask/_internal/dom/serializers/json.py
webtask/_internal/llm/__init__.py
webtask/_internal/llm/json_schema_utils.py
webtask/_internal/prompts/__init__.py
webtask/_internal/prompts/markdown_builder.py
pywebtask-0.27.0.dist-info/METADATA
pywebtask-0.27.0.dist-info/WHEEL
pywebtask-0.27.0.dist-info/top_level.txt
pywebtask-0.27.0.dist-info/RECORD
