Metadata-Version: 2.4
Name: pywebtask
Version: 0.27.0
Summary: LLM-powered web automation library with autonomous agents
Author: Steve Wang
License: MIT
Project-URL: Homepage, https://github.com/steve-z-wang/webtask
Project-URL: Repository, https://github.com/steve-z-wang/webtask
Project-URL: Issues, https://github.com/steve-z-wang/webtask/issues
Project-URL: Documentation, https://steve-z-wang.github.io/webtask/
Keywords: automation,web-automation,browser-automation,llm,ai-agent,playwright,web-agent,natural-language
Classifier: Development Status :: 3 - Alpha
Classifier: Intended Audience :: Developers
Classifier: License :: OSI Approved :: MIT License
Classifier: Programming Language :: Python :: 3
Classifier: Programming Language :: Python :: 3.10
Classifier: Programming Language :: Python :: 3.11
Classifier: Programming Language :: Python :: 3.12
Classifier: Programming Language :: Python :: 3.13
Classifier: Programming Language :: Python :: 3.14
Classifier: Topic :: Software Development :: Libraries :: Python Modules
Classifier: Topic :: Internet :: WWW/HTTP :: Browsers
Classifier: Topic :: Scientific/Engineering :: Artificial Intelligence
Requires-Python: >=3.10
License-File: LICENSE
Requires-Dist: pydantic>=2.0.0
Requires-Dist: pyyaml>=6.0
Requires-Dist: openai>=1.0.0
Requires-Dist: google-genai>=1.0.0
Requires-Dist: playwright>=1.40.0
Requires-Dist: lxml>=4.9.0
Requires-Dist: tiktoken>=0.5.0
Requires-Dist: Pillow>=10.0.0
Provides-Extra: bedrock
Requires-Dist: boto3>=1.28.0; extra == "bedrock"
Provides-Extra: mcp
Requires-Dist: mcp>=0.1.0; extra == "mcp"
Provides-Extra: dev
Requires-Dist: pytest>=7.0.0; extra == "dev"
Requires-Dist: pytest-asyncio>=0.21.0; extra == "dev"
Requires-Dist: pytest-mock>=3.12.0; extra == "dev"
Requires-Dist: pytest-cov>=4.1.0; extra == "dev"
Requires-Dist: pytest-xdist>=3.0.0; extra == "dev"
Requires-Dist: black>=23.0.0; extra == "dev"
Requires-Dist: ruff>=0.1.0; extra == "dev"
Requires-Dist: pdm>=2.0.0; extra == "dev"
Requires-Dist: python-dotenv>=1.0.0; extra == "dev"
Provides-Extra: docs
Requires-Dist: mkdocs-material>=9.5.0; extra == "docs"
Dynamic: license-file
